FIFO/FIFO_single_cycle/FIFO.V
module fifo(clk,rst,data_in,data_out,we_en,rd_en,buf_full,buf_empty,fifo_counter);
input clk,rst,we_en,rd_en;
input [7:0] data_in;
output reg [7:0] data_out;
output  buf_empty,buf_full;
output reg [6:0] fifo_counter;


reg [7:0] buf_mem[0:63];
reg [5:0] rd_ptr,wr_ptr;



assign buf_empty = (fifo_counter==0);
assign buf_full  = (fifo_counter==64);

always @(posedge clk or posedge rst)
begin
    if(rst)
        fifo_counter <= 0;

    else begin
        case ({we_en && !buf_full, rd_en && !buf_empty})

            2'b10:
                fifo_counter <= fifo_counter + 1;

            2'b01:
                fifo_counter <= fifo_counter - 1;

            2'b11:
                fifo_counter <= fifo_counter;

            default:
                fifo_counter <= fifo_counter;

        endcase
    end
end

always @(posedge clk or posedge rst)begin
    if(rst)
        data_out<=0;
    else if(rd_en && !buf_empty)
        data_out<=buf_mem[rd_ptr];
end

always @ (posedge clk)
begin
    if(we_en && !buf_full)
        buf_mem[wr_ptr]<=data_in;
end

always @ (posedge clk or posedge rst)
begin
    if(rst) begin
        wr_ptr<=0;
        rd_ptr<=0;
    end
    else begin
        if(rd_en && !buf_empty )
            rd_ptr<=rd_ptr+1;
        if(we_en && !buf_full)
            wr_ptr<=wr_ptr+1;
    end    
end
endmodule

FIFO/FIFO_single_cycle/FIFO_TB.V
`timescale 1ns/1ps

module fifo_tb;

reg clk;
reg rst;
reg we_en;
reg rd_en;
reg [7:0] data_in;

wire [7:0] data_out;
wire buf_full;
wire buf_empty;
wire [6:0] fifo_counter;

fifo dut (
    .clk(clk),
    .rst(rst),
    .data_in(data_in),
    .data_out(data_out),
    .we_en(we_en),
    .rd_en(rd_en),
    .buf_full(buf_full),
    .buf_empty(buf_empty),
    .fifo_counter(fifo_counter)
);



initial begin
    clk = 0;
    forever #5 clk = ~clk;
end


// Test Sequence
initial begin
    
    $dumpfile("fifo.vcd");
    $dumpvars(0, fifo_tb);


    // Initialize
    rst = 1;
    we_en = 0;
    rd_en = 0;
    data_in = 0;

    #20;
    rst = 0;

   
    // Write 10 values
   

    $display("Writing Data...");

    repeat(60)
    begin
        @(posedge clk);
        we_en = 1;
        data_in = data_in + 8'd1;
    end

    @(posedge clk);
    we_en = 0;

    #20;

    
    // Read 10 values
    
    $display("Reading Data...");

    repeat(10)
    begin
        @(posedge clk);
        rd_en = 1;
    end

    @(posedge clk);
    rd_en = 0;

    #20;

   
    // Simultaneous Read & Write
    

    $display("Simultaneous Read and Write...");

    repeat(5)
    begin
        @(posedge clk);
        we_en = 1;
        rd_en = 1;
        data_in = data_in + 8'd1;
    end

    @(posedge clk);
    we_en = 0;
    rd_en = 0;

    #50;

    $finish;

end



initial begin
    $monitor(
        "Time=%0t rst=%b we=%b rd=%b din=%d dout=%d count=%d full=%b empty=%b",
        $time,
        rst,
        we_en,
        rd_en,
        data_in,
        data_out,
        fifo_counter,
        buf_full,
        buf_empty
    );
end

endmodule

FIFO/FIFO_single_cycle/fifo.vcd
$date
	Sat May 30 15:41:39 2026
$end
$version
	Icarus Verilog
$end
$timescale
	1ps
$end
$scope module fifo_tb $end
$var wire 7 ! fifo_counter [6:0] $end
$var wire 8 " data_out [7:0] $end
$var wire 1 # buf_full $end
$var wire 1 $ buf_empty $end
$var reg 1 % clk $end
$var reg 8 & data_in [7:0] $end
$var reg 1 ' rd_en $end
$var reg 1 ( rst $end
$var reg 1 ) we_en $end
$scope module dut $end
$var wire 1 % clk $end
$var wire 8 * data_in [7:0] $end
$var wire 1 ' rd_en $end
$var wire 1 ( rst $end
$var wire 1 ) we_en $end
$var wire 1 # buf_full $end
$var wire 1 $ buf_empty $end
$var reg 8 + data_out [7:0] $end
$var reg 7 , fifo_counter [6:0] $end
$var reg 6 - rd_ptr [5:0] $end
$var reg 6 . wr_ptr [5:0] $end
$upscope $end
$upscope $end
$enddefinitions $end
#0
$dumpvars
b0 .
b0 -
b0 ,
b0 +
b0 *
0)
1(
0'
b0 &
0%
1$
0#
b0 "
b0 !
$end
#5000
1%
#10000
0%
#15000
1%
#20000
0%
0(
#25000
b1 .
0$
b1 !
b1 ,
b1 &
b1 *
1)
1%
#30000
0%
#35000
b10 !
b10 ,
b10 .
b10 &
b10 *
1%
#40000
0%
#45000
b11 .
b11 !
b11 ,
b11 &
b11 *
1%
#50000
0%
#55000
b100 !
b100 ,
b100 .
b100 &
b100 *
1%
#60000
0%
#65000
b101 .
b101 !
b101 ,
b101 &
b101 *
1%
#70000
0%
#75000
b110 !
b110 ,
b110 .
b110 &
b110 *
1%
#80000
0%
#85000
b111 .
b111 !
b111 ,
b111 &
b111 *
1%
#90000
0%
#95000
b1000 !
b1000 ,
b1000 .
b1000 &
b1000 *
1%
#100000
0%
#105000
b1001 .
b1001 !
b1001 ,
b1001 &
b1001 *
1%
#110000
0%
#115000
b1010 !
b1010 ,
b1010 .
b1010 &
b1010 *
1%
#120000
0%
#125000
b1011 .
b1011 !
b1011 ,
b1011 &
b1011 *
1%
#130000
0%
#135000
b1100 !
b1100 ,
b1100 .
b1100 &
b1100 *
1%
#140000
0%
#145000
b1101 .
b1101 !
b1101 ,
b1101 &
b1101 *
1%
#150000
0%
#155000
b1110 !
b1110 ,
b1110 .
b1110 &
b1110 *
1%
#160000
0%
#165000
b1111 .
b1111 !
b1111 ,
b1111 &
b1111 *
1%
#170000
0%
#175000
b10000 !
b10000 ,
b10000 .
b10000 &
b10000 *
1%
#180000
0%
#185000
b10001 .
b10001 !
b10001 ,
b10001 &
b10001 *
1%
#190000
0%
#195000
b10010 !
b10010 ,
b10010 .
b10010 &
b10010 *
1%
#200000
0%
#205000
b10011 .
b10011 !
b10011 ,
b10011 &
b10011 *
1%
#210000
0%
#215000
b10100 !
b10100 ,
b10100 .
b10100 &
b10100 *
1%
#220000
0%
#225000
b10101 .
b10101 !
b10101 ,
b10101 &
b10101 *
1%
#230000
0%
#235000
b10110 !
b10110 ,
b10110 .
b10110 &
b10110 *
1%
#240000
0%
#245000
b10111 .
b10111 !
b10111 ,
b10111 &
b10111 *
1%
#250000
0%
#255000
b11000 !
b11000 ,
b11000 .
b11000 &
b11000 *
1%
#260000
0%
#265000
b11001 .
b11001 !
b11001 ,
b11001 &
b11001 *
1%
#270000
0%
#275000
b11010 !
b11010 ,
b11010 .
b11010 &
b11010 *
1%
#280000
0%
#285000
b11011 .
b11011 !
b11011 ,
b11011 &
b11011 *
1%
#290000
0%
#295000
b11100 !
b11100 ,
b11100 .
b11100 &
b11100 *
1%
#300000
0%
#305000
b11101 .
b11101 !
b11101 ,
b11101 &
b11101 *
1%
#310000
0%
#315000
b11110 !
b11110 ,
b11110 .
b11110 &
b11110 *
1%
#320000
0%
#325000
b11111 .
b11111 !
b11111 ,
b11111 &
b11111 *
1%
#330000
0%
#335000
b100000 !
b100000 ,
b100000 .
b100000 &
b100000 *
1%
#340000
0%
#345000
b100001 .
b100001 !
b100001 ,
b100001 &
b100001 *
1%
#350000
0%
#355000
b100010 !
b100010 ,
b100010 .
b100010 &
b100010 *
1%
#360000
0%
#365000
b100011 .
b100011 !
b100011 ,
b100011 &
b100011 *
1%
#370000
0%
#375000
b100100 !
b100100 ,
b100100 .
b100100 &
b100100 *
1%
#380000
0%
#385000
b100101 .
b100101 !
b100101 ,
b100101 &
b100101 *
1%
#390000
0%
#395000
b100110 !
b100110 ,
b100110 .
b100110 &
b100110 *
1%
#400000
0%
#405000
b100111 .
b100111 !
b100111 ,
b100111 &
b100111 *
1%
#410000
0%
#415000
b101000 !
b101000 ,
b101000 .
b101000 &
b101000 *
1%
#420000
0%
#425000
b101001 .
b101001 !
b101001 ,
b101001 &
b101001 *
1%
#430000
0%
#435000
b101010 !
b101010 ,
b101010 .
b101010 &
b101010 *
1%
#440000
0%
#445000
b101011 .
b101011 !
b101011 ,
b101011 &
b101011 *
1%
#450000
0%
#455000
b101100 !
b101100 ,
b101100 .
b101100 &
b101100 *
1%
#460000
0%
#465000
b101101 .
b101101 !
b101101 ,
b101101 &
b101101 *
1%
#470000
0%
#475000
b101110 !
b101110 ,
b101110 .
b101110 &
b101110 *
1%
#480000
0%
#485000
b101111 .
b101111 !
b101111 ,
b101111 &
b101111 *
1%
#490000
0%
#495000
b110000 !
b110000 ,
b110000 .
b110000 &
b110000 *
1%
#500000
0%
#505000
b110001 .
b110001 !
b110001 ,
b110001 &
b110001 *
1%
#510000
0%
#515000
b110010 !
b110010 ,
b110010 .
b110010 &
b110010 *
1%
#520000
0%
#525000
b110011 .
b110011 !
b110011 ,
b110011 &
b110011 *
1%
#530000
0%
#535000
b110100 !
b110100 ,
b110100 .
b110100 &
b110100 *
1%
#540000
0%
#545000
b110101 .
b110101 !
b110101 ,
b110101 &
b110101 *
1%
#550000
0%
#555000
b110110 !
b110110 ,
b110110 .
b110110 &
b110110 *
1%
#560000
0%
#565000
b110111 .
b110111 !
b110111 ,
b110111 &
b110111 *
1%
#570000
0%
#575000
b111000 !
b111000 ,
b111000 .
b111000 &
b111000 *
1%
#580000
0%
#585000
b111001 .
b111001 !
b111001 ,
b111001 &
b111001 *
1%
#590000
0%
#595000
b111010 !
b111010 ,
b111010 .
b111010 &
b111010 *
1%
#600000
0%
#605000
b111011 .
b111011 !
b111011 ,
b111011 &
b111011 *
1%
#610000
0%
#615000
b111100 !
b111100 ,
b111100 .
b111100 &
b111100 *
1%
#620000
0%
#625000
b111101 .
b111101 !
b111101 ,
b111101 &
b111101 *
1%
#630000
0%
#635000
b111110 !
b111110 ,
b111110 .
b111110 &
b111110 *
1%
#640000
0%
#645000
b111111 .
b111111 !
b111111 ,
b111111 &
b111111 *
1%
#650000
0%
#655000
1#
b1000000 !
b1000000 ,
b0 .
b1000000 &
b1000000 *
1%
#660000
0%
#665000
b1000001 &
b1000001 *
1%
#670000
0%
#675000
b1000010 &
b1000010 *
1%
#680000
0%
#685000
b1000011 &
b1000011 *
1%
#690000
0%
#695000
b1000100 &
b1000100 *
1%
#700000
0%
#705000
b1000101 &
b1000101 *
1%
#710000
0%
#715000
b1000110 &
b1000110 *
1%
#720000
0%
#725000
0)
1%
#730000
0%
#735000
1%
#740000
0%
#745000
b1 -
b1 "
b1 +
0#
b111111 !
b111111 ,
1'
1%
#750000
0%
#755000
b111110 !
b111110 ,
b10 -
1%
#760000
0%
#765000
b11 -
b11 "
b11 +
b111101 !
b111101 ,
1%
#770000
0%
#775000
b111100 !
b111100 ,
b100 -
1%
#780000
0%
#785000
b101 -
b101 "
b101 +
b111011 !
b111011 ,
1%
#790000
0%
#795000
b111010 !
b111010 ,
b110 -
1%
#800000
0%
#805000
b111 -
b111 "
b111 +
b111001 !
b111001 ,
1%
#810000
0%
#815000
b111000 !
b111000 ,
b1000 -
1%
#820000
0%
#825000
b1001 -
b1001 "
b1001 +
b110111 !
b110111 ,
1%
#830000
0%
#835000
b110110 !
b110110 ,
b1010 -
1%
#840000
0%
#845000
0'
1%
#850000
0%
#855000
1%
#860000
0%
#865000
b1 .
b1011 -
b1011 "
b1011 +
b1000111 &
b1000111 *
1'
1)
1%
#870000
0%
#875000
b10 .
b1100 -
b1001000 &
b1001000 *
1%
#880000
0%
#885000
b11 .
b1101 -
b1101 "
b1101 +
b1001001 &
b1001001 *
1%
#890000
0%
#895000
b100 .
b1110 -
b1001010 &
b1001010 *
1%
#900000
0%
#905000
b101 .
b1111 -
b1111 "
b1111 +
b1001011 &
b1001011 *
1%
#910000
0%
#915000
0'
0)
1%
