4_bit_ripple_up_counter/RTL/dff.v
module dff(
    input clk,
    input reset,
    input d,
    output reg q
);
always @ (negedge clk or posedge reset)
begin
    if(reset)
        q<=1'b0;
    else
        q<=d;
end
endmodule

4_bit_ripple_up_counter/RTL/tff.v
module tff(
    input clk,
    input reset,
    output q
);
wire d;
assign d = ~q;
dff uut(.d(d),.clk(clk),.reset(reset),.q(q));
endmodule

4_bit_ripple_up_counter/RTL/ripple_counter.v
module ripple_counter(
    input clk,
    input reset,
    output [3:0] q
);

tff uut1(.q(q[0]),.clk(clk),.reset(reset));
tff uut2(.q(q[1]),.clk(q[0]),.reset(reset));
tff uut3(.q(q[2]),.clk(q[1]),.reset(reset));
tff uut4(.q(q[3]),.clk(q[2]),.reset(reset));
endmodule

4_bit_ripple_up_counter/TB/ripple_counter_tb.v
module ripple_counter_tb;

reg clk;
reg reset;
wire [3:0] q;

ripple_counter uut(
    .clk(clk),
    .reset(reset),
    .q(q)
);

initial begin
    clk = 1'b0;
end

always #5 clk = ~clk;

initial begin

    $dumpfile("ripple_counter_tb.vcd");
    $dumpvars(0, ripple_counter_tb);

    reset = 1'b1;

    #15;
    reset = 1'b0;

   #90;

    $display("test completed");

    $finish;

end

initial begin
    $monitor("time=%0t clk=%b reset=%b q=%b",
              $time, clk, reset, q);
end

endmodule

4_bit_ripple_up_counter/WAVEFORM/ripple_counter_tb.vcd
$date
	Thu May 28 15:03:42 2026
$end
$version
	Icarus Verilog
$end
$timescale
	1s
$end
$scope module ripple_counter_tb $end
$var wire 4 ! q [3:0] $end
$var reg 1 " clk $end
$var reg 1 # reset $end
$scope module uut $end
$var wire 1 " clk $end
$var wire 1 # reset $end
$var wire 4 $ q [3:0] $end
$scope module uut1 $end
$var wire 1 " clk $end
$var wire 1 % d $end
$var wire 1 # reset $end
$var wire 1 & q $end
$scope module uut $end
$var wire 1 " clk $end
$var wire 1 % d $end
$var wire 1 # reset $end
$var reg 1 & q $end
$upscope $end
$upscope $end
$scope module uut2 $end
$var wire 1 ' clk $end
$var wire 1 ( d $end
$var wire 1 # reset $end
$var wire 1 ) q $end
$scope module uut $end
$var wire 1 ' clk $end
$var wire 1 ( d $end
$var wire 1 # reset $end
$var reg 1 ) q $end
$upscope $end
$upscope $end
$scope module uut3 $end
$var wire 1 * clk $end
$var wire 1 + d $end
$var wire 1 # reset $end
$var wire 1 , q $end
$scope module uut $end
$var wire 1 * clk $end
$var wire 1 + d $end
$var wire 1 # reset $end
$var reg 1 , q $end
$upscope $end
$upscope $end
$scope module uut4 $end
$var wire 1 - clk $end
$var wire 1 . d $end
$var wire 1 # reset $end
$var wire 1 / q $end
$scope module uut $end
$var wire 1 - clk $end
$var wire 1 . d $end
$var wire 1 # reset $end
$var reg 1 / q $end
$upscope $end
$upscope $end
$upscope $end
$upscope $end
$enddefinitions $end
#0
$dumpvars
0/
1.
0-
0,
1+
0*
0)
1(
0'
0&
1%
b0 $
1#
0"
b0 !
$end
#5
1"
#10
0"
#15
1"
0#
#20
0%
1'
b1 !
b1 $
1&
0"
#25
1"
#30
0(
1*
1)
1%
0'
b10 !
b10 $
0&
0"
#35
1"
#40
0%
1'
b11 !
b11 $
1&
0"
#45
1"
#50
0+
1-
1,
1(
0*
0)
1%
0'
b100 !
b100 $
0&
0"
#55
1"
#60
0%
1'
b101 !
b101 $
1&
0"
#65
1"
#70
0(
1*
1)
1%
0'
b110 !
b110 $
0&
0"
#75
1"
#80
0%
1'
b111 !
b111 $
1&
0"
#85
1"
#90
0.
1/
1+
0-
0,
1(
0*
0)
1%
0'
b1000 !
b1000 $
0&
0"
#95
1"
#100
0%
1'
b1001 !
b1001 $
1&
0"
