cache_controller_project/rtl/cache_controller.v
module cache_controller(
    input clk,
    input rst,

    input cpu_req,
    input hit,

    input cpu_write,

    input dirty,

    output reg [2:0] state,

    output reg mem_read,
    output reg tag_write_en,
    output reg data_write_en,
    output reg cpu_ready,

    output reg dirty_write_en,

    output reg mem_write
);

parameter IDLE        = 3'd0,
          COMPARE_TAG = 3'd1,
          WRITE_HIT   = 3'd2,
          MISS        = 3'd3,
          WRITE_BACK = 3'd4,
          ALLOCATE   = 3'd5,
          DONE       = 3'd6;
          
          

reg [2:0] next_state;

always @(posedge clk or posedge rst)
begin
    if(rst)
        state <= IDLE;
    else
        state <= next_state;
end

always @(*) begin
    case(state)
        IDLE:
            begin
            if(cpu_req)
                next_state = COMPARE_TAG;
            else
                next_state = IDLE;
        end
        COMPARE_TAG:
        begin
            if(hit)
            begin
                if(cpu_write)
                    next_state = WRITE_HIT;
                else
                    next_state = DONE;
            end
            else
                next_state = MISS;
        end

        WRITE_HIT:
        begin
            next_state = DONE;
        end
        WRITE_BACK:
        begin
            next_state = ALLOCATE;
        end
        MISS:
        begin
        if(dirty)
            next_state = WRITE_BACK;
        else
            next_state = ALLOCATE;
        end
        ALLOCATE:
        begin
            next_state = DONE;
        end
        DONE:
        begin
            next_state = IDLE;
        end

        default:
            next_state = IDLE;
    endcase
end

always @(*)
begin
    mem_read      = 0;
    tag_write_en  = 0;
    data_write_en = 0;
    cpu_ready     = 0;
    dirty_write_en = 0;
    mem_write = 0;
    case(state)
        MISS:
        begin
            mem_read = 1;
        end
        ALLOCATE:
        begin
            tag_write_en  = 1;
            data_write_en = 1;
        end
        WRITE_HIT:
        begin
            data_write_en  = 1;
            dirty_write_en = 1;
        end
        WRITE_BACK:
        begin
           mem_write = 1;
        end
        DONE:
        begin
            cpu_ready = 1;
        end
    endcase
end
endmodule

cache_controller_project/tb/tb_cache_controller_writeback.v
`timescale 1ns/1ps

module tb_cache_controller_writeback;

reg clk;
reg rst;

reg cpu_req;
reg cpu_write;

reg hit;
reg dirty;

wire [2:0] state;

wire mem_read;
wire mem_write;

wire tag_write_en;
wire data_write_en;
wire dirty_write_en;

wire cpu_ready;

cache_controller dut(

    .clk(clk),
    .rst(rst),

    .cpu_req(cpu_req),
    .cpu_write(cpu_write),

    .hit(hit),
    .dirty(dirty),

    .state(state),

    .mem_read(mem_read),
    .mem_write(mem_write),

    .tag_write_en(tag_write_en),
    .data_write_en(data_write_en),

    .dirty_write_en(dirty_write_en),

    .cpu_ready(cpu_ready)

);

always #5 clk = ~clk;

initial begin

    $dumpfile("cache_controller_writeback.vcd");
    $dumpvars(0,tb_cache_controller_writeback);

end

initial begin

    clk = 0;

    rst = 1;

    cpu_req = 0;
    cpu_write = 0;

    hit = 0;
    dirty = 0;

    #10;

    rst = 0;

    //--------------------------------
    // CASE 1
    // MISS + CLEAN
    //--------------------------------

    cpu_req = 1;

    hit = 0;
    dirty = 0;

    #50;

    //--------------------------------
    // CASE 2
    // WRITE HIT
    //--------------------------------

    cpu_write = 1;
    hit = 1;

    #30;

    //--------------------------------
    // CASE 3
    // MISS + DIRTY
    //--------------------------------

    cpu_write = 0;

    hit = 0;
    dirty = 1;

    #60;

    $finish;

end

initial begin

    $monitor(
"Time=%0t state=%d hit=%b dirty=%b mem_read=%b mem_write=%b dirty_we=%b",
        $time,
        state,
        hit,
        dirty,
        mem_read,
        mem_write,
        dirty_write_en
    );

end

endmodule

cache_controller_project/waves/cache_controller_writeback.vcd
$date
	Wed Jun 24 18:07:03 2026
$end
$version
	Icarus Verilog
$end
$timescale
	1ps
$end
$scope module tb_cache_controller_writeback $end
$var wire 1 ! tag_write_en $end
$var wire 3 " state [2:0] $end
$var wire 1 # mem_write $end
$var wire 1 $ mem_read $end
$var wire 1 % dirty_write_en $end
$var wire 1 & data_write_en $end
$var wire 1 ' cpu_ready $end
$var reg 1 ( clk $end
$var reg 1 ) cpu_req $end
$var reg 1 * cpu_write $end
$var reg 1 + dirty $end
$var reg 1 , hit $end
$var reg 1 - rst $end
$scope module dut $end
$var wire 1 ( clk $end
$var wire 1 ) cpu_req $end
$var wire 1 * cpu_write $end
$var wire 1 + dirty $end
$var wire 1 , hit $end
$var wire 1 - rst $end
$var reg 1 ' cpu_ready $end
$var reg 1 & data_write_en $end
$var reg 1 % dirty_write_en $end
$var reg 1 $ mem_read $end
$var reg 1 # mem_write $end
$var reg 3 . next_state [2:0] $end
$var reg 3 / state [2:0] $end
$var reg 1 ! tag_write_en $end
$upscope $end
$upscope $end
$enddefinitions $end
#0
$dumpvars
b0 /
b0 .
1-
0,
0+
0*
0)
0(
0'
0&
0%
0$
0#
b0 "
0!
$end
#5000
1(
#10000
b1 .
0(
1)
0-
#15000
b11 .
b1 "
b1 /
1(
#20000
0(
#25000
1$
b101 .
b11 "
b11 /
1(
#30000
0(
#35000
1&
1!
0$
b110 .
b101 "
b101 /
1(
#40000
0(
#45000
1'
0&
0!
b0 .
b110 "
b110 /
1(
#50000
0(
#55000
0'
b1 .
b0 "
b0 /
1(
#60000
0(
1,
1*
#65000
b10 .
b1 "
b1 /
1(
#70000
0(
#75000
1%
1&
b110 .
b10 "
b10 /
1(
#80000
0(
#85000
1'
0%
0&
b0 .
b110 "
b110 /
1(
#90000
0(
1+
0,
0*
#95000
0'
b1 .
b0 "
b0 /
1(
#100000
0(
#105000
b11 .
b1 "
b1 /
1(
#110000
0(
#115000
1$
b100 .
b11 "
b11 /
1(
#120000
0(
#125000
1#
0$
b101 .
b100 "
b100 /
1(
#130000
0(
#135000
1&
1!
0#
b110 .
b101 "
b101 /
1(
#140000
0(
#145000
1'
0&
0!
b0 .
b110 "
b110 /
1(
