cache_controller_project/rtl/dirty_array.v
module dirty_array(

    input clk,
    input write_en,

    input dirty_in,
    input [1:0] index,

    output wire dirty_out

);

reg dirty_mem [0:3];

integer i;

initial begin

    for(i=0;i<4;i=i+1)
        dirty_mem[i] = 0;

end

always @(posedge clk)
begin

    if(write_en)
        dirty_mem[index] <= dirty_in;

end

assign dirty_out = dirty_mem[index];

endmodule

cache_controller_project/rtl/main_memory.v
module  main_memory (
    input clk,
    input [31:0] addr,
    input mem_read,
    input mem_write,
    input [127:0] write_block,
    output reg [127:0] block_data,
    output reg mem_ready
);
reg [31:0] mem [0:255];
integer i;
initial begin
    for(i=0;i<256;i=i+1)
        mem[i]=i;
end
wire [31:0] block_addr;
assign block_addr = {addr[31:2],2'b00};
always @(posedge clk)
begin
    mem_ready <= 0;
    if(mem_read)
    begin
        block_data <= {
            mem[block_addr + 3],
            mem[block_addr + 2],
            mem[block_addr + 1],
            mem[block_addr]
        };
        mem_ready <= 1;
    end
    if(mem_write)
    begin
        mem[block_addr]     <= write_block[31:0];
        mem[block_addr + 1] <= write_block[63:32];
        mem[block_addr + 2] <= write_block[95:64];
        mem[block_addr + 3] <= write_block[127:96];
        mem_ready <= 1;
    end
end
endmodule

cache_controller_project/rtl/data_array.v
module data_array(
    input clk,
    input write_en,
    input [1:0] index,
    input write_word_en,
    input [31:0] write_data,
    input [1:0] offset,
    input [127:0] block_in,
    output [127:0] block_out
);
reg [127:0] data_mem [0:3];
integer i;

initial begin
    for(i=0;i<4;i=i+1)
        data_mem[i] = 0;
end
always @(posedge clk)
begin

    // Cache refill
    if(write_en)
    begin
        data_mem[index] <= block_in;
    end

    // CPU write hit
    if(write_word_en)
    begin

        case(offset)

            2'b00:
                data_mem[index][31:0] <= write_data;

            2'b01:
                data_mem[index][63:32] <= write_data;

            2'b10:
                data_mem[index][95:64] <= write_data;

            2'b11:
                data_mem[index][127:96] <= write_data;

        endcase

    end

end
assign block_out = data_mem[index];
endmodule

cache_controller_project/rtl/tag_array.v
module tag_array (
    input clk ,
    input write_en,

    input [3:0] tag_in,
    input valid_in,

    input [1:0] index,

    output wire [3:0] tag_out,
    output wire valid_out
);

reg [3:0] tag_mem [0:3];
reg valid_mem [0:3];

integer i;

initial begin
    for(i=0;i<4;i=i+1)
    begin
        tag_mem[i]   = 0;
        valid_mem[i] = 0;
    end
end

always @(posedge clk)
begin
    if(write_en)
    begin
        tag_mem[index] <= tag_in;
        valid_mem[index] <= valid_in;
    end
end
assign tag_out = tag_mem[index];
assign valid_out = valid_mem[index];    
endmodule

cache_controller_project/rtl/cache_controller.v
module cache_controller(
    input clk,
    input rst,

    input cpu_req,
    input hit,

    input cpu_write,

    input dirty,

    output reg [2:0] state,

    output reg mem_read,
    output reg tag_write_en,
    output reg data_write_en,
    output reg cpu_ready,

    output reg dirty_write_en,

    output reg mem_write
);

parameter IDLE        = 3'd0,
          COMPARE_TAG = 3'd1,
          WRITE_HIT   = 3'd2,
          MISS        = 3'd3,
          WRITE_BACK = 3'd4,
          ALLOCATE   = 3'd5,
          DONE       = 3'd6;
          
          

reg [2:0] next_state;

always @(posedge clk or posedge rst)
begin
    if(rst)
        state <= IDLE;
    else
        state <= next_state;
end

always @(*) begin
    case(state)
        IDLE:
            begin
            if(cpu_req)
                next_state = COMPARE_TAG;
            else
                next_state = IDLE;
        end
        COMPARE_TAG:
        begin
            if(hit)
            begin
                if(cpu_write)
                    next_state = WRITE_HIT;
                else
                    next_state = DONE;
            end
            else
                next_state = MISS;
        end

        WRITE_HIT:
        begin
            next_state = DONE;
        end
        WRITE_BACK:
        begin
            next_state = ALLOCATE;
        end
        MISS:
        begin
        if(dirty)
            next_state = WRITE_BACK;
        else
            next_state = ALLOCATE;
        end
        ALLOCATE:
        begin
            next_state = DONE;
        end
        DONE:
        begin
            next_state = IDLE;
        end

        default:
            next_state = IDLE;
    endcase
end

always @(*)
begin
    mem_read      = 0;
    tag_write_en  = 0;
    data_write_en = 0;
    cpu_ready     = 0;
    dirty_write_en = 0;
    mem_write = 0;
    case(state)
        MISS:
        begin
            mem_read = 1;
        end
        ALLOCATE:
        begin
            tag_write_en  = 1;
            data_write_en = 1;
        end
        WRITE_HIT:
        begin
            data_write_en  = 1;
            dirty_write_en = 1;
        end
        WRITE_BACK:
        begin
           mem_write = 1;
        end
        DONE:
        begin
            cpu_ready = 1;
        end
    endcase
end
endmodule

cache_controller_project/rtl/cache_lookup.v
module cache_lookup(
    input [7:0] addr,

    input [3:0] stored_tag,
    input valid,

    output [3:0] tag,
    output [1:0] index,
    output [1:0] offset,

    output hit
);

assign tag    = addr[7:4];
assign index  = addr[3:2];
assign offset = addr[1:0];

assign hit = (valid && (stored_tag == tag));

endmodule

cache_controller_project/rtl/cache_stats.v
module cache_stats(

    input clk,
    input rst,

    input hit,
    input miss,

    output reg [31:0] hit_count,
    output reg [31:0] miss_count

);

always @(posedge clk or posedge rst)
begin

    if(rst)
    begin
        hit_count  <= 0;
        miss_count <= 0;
    end
    else
    begin

        if(hit)
            hit_count <= hit_count + 1;

        if(miss)
            miss_count <= miss_count + 1;

    end

end

endmodule

cache_controller_project/rtl/cache_top.v
module cache_top(
    input clk,
    input rst,
    input cpu_write,
    input cpu_req,
    input [7:0] addr,

    output hit ,
    output [2:0] state,
    output [31:0] hit_count,
    output [31:0] miss_count
);


wire [3:0] tag;
wire [1:0] index;
wire [1:0] offset;

wire [3:0] stored_tag;
wire valid;

wire mem_read;
wire tag_write_en;
wire data_write_en;
wire cpu_ready;

wire [127:0] block_data;
wire [127:0] cache_block;

wire dirty;
wire dirty_write_en;
wire mem_write;

wire miss;
assign miss = cpu_req & ~hit;

cache_stats stats_inst(

    .clk(clk),
    .rst(rst),

    .hit(hit),
    .miss(miss),

    .hit_count(hit_count),
    .miss_count(miss_count)

);
cache_lookup lookup_inst(

    .addr(addr),

    .stored_tag(stored_tag),
    .valid(valid),

    .tag(tag),
    .index(index),
    .offset(offset),

    .hit(hit)

);


cache_controller ctrl_inst(

    .clk(clk),
    .rst(rst),

    .cpu_req(cpu_req),
    .hit(hit),

    .state(state),

    .cpu_write(cpu_write),

    .mem_read(mem_read),
    .tag_write_en(tag_write_en),
    .data_write_en(data_write_en),

    .cpu_ready(cpu_ready),

    .dirty(dirty),
    .dirty_write_en(dirty_write_en),

    .mem_write(mem_write)

);
tag_array tag_inst(

    .clk(clk),

    .write_en(tag_write_en),

    .tag_in(tag),

    .valid_in(1'b1),

    .index(index),

    .tag_out(stored_tag),
    .valid_out(valid)

);

data_array data_inst(

    .clk(clk),

    .write_en(data_write_en),

    .index(index),

    .block_in(block_data),

    .block_out(cache_block)

);
main_memory mem_inst(

    .clk(clk),

    .addr({24'd0,addr}),

    .mem_read(mem_read),
    .mem_write(mem_write),

    .write_block(cache_block),

    .block_data(block_data),

    .mem_ready()

);

dirty_array dirty_inst(

    .clk(clk),

    .write_en(dirty_write_en),

    .index(index),

    .dirty_in(1'b1),

    .dirty_out(dirty)

);

endmodule

cache_controller_project/tb/tb_final_cache_system.v
`timescale 1ns/1ps

module tb_final_cache_system;

reg clk;
reg rst;

reg cpu_req;
reg cpu_write;

reg [7:0] addr;

wire hit;
wire [2:0] state;

cache_top dut(

    .clk(clk),
    .rst(rst),

    .cpu_write(cpu_write),
    .cpu_req(cpu_req),

    .addr(addr),

    .hit(hit),
    .state(state)

);

always #5 clk = ~clk;

initial begin

    $dumpfile("final_cache_system.vcd");
    $dumpvars(0, tb_final_cache_system);

    clk = 0;
    rst = 1;

    cpu_req   = 0;
    cpu_write = 0;
    addr      = 0;

    #20;
    rst = 0;

    //----------------------------------
    // TEST 1 : COLD MISS
    //----------------------------------

    $display("\n========== TEST 1 : COLD MISS ==========\n");

    addr = 8'd6;
    cpu_req = 1;

    #40;

    cpu_req = 0;

    //----------------------------------
    // TEST 2 : CACHE HIT
    //----------------------------------

    #20;

    $display("\n========== TEST 2 : CACHE HIT ==========\n");

    addr = 8'd6;
    cpu_req = 1;

    #30;

    cpu_req = 0;

    //----------------------------------
    // TEST 3 : WRITE HIT
    //----------------------------------

    #20;

    $display("\n========== TEST 3 : WRITE HIT ==========\n");

    addr = 8'd6;

    cpu_write = 1;
    cpu_req   = 1;

    #30;

    cpu_req   = 0;
    cpu_write = 0;

    //----------------------------------
    // TEST 4 : DIRTY MISS
    //----------------------------------

    #20;

    $display("\n========== TEST 4 : DIRTY MISS ==========\n");

    // same index, different tag
    addr = 8'd22;

    cpu_req = 1;

    #60;

    cpu_req = 0;

    //----------------------------------
    // FINISH
    //----------------------------------

    #50;

    $finish;

end

initial begin

    $monitor(
    "Time=%0t Addr=%d Hit=%b State=%d",
    $time,
    addr,
    hit,
    state
    );

end

endmodule

cache_controller_project/waves/final_cache_system.vcd
$date
	Wed Jun 24 18:31:55 2026
$end
$version
	Icarus Verilog
$end
$timescale
	1ps
$end
$scope module tb_final_cache_system $end
$var wire 3 ! state [2:0] $end
$var wire 1 " hit $end
$var reg 8 # addr [7:0] $end
$var reg 1 $ clk $end
$var reg 1 % cpu_req $end
$var reg 1 & cpu_write $end
$var reg 1 ' rst $end
$scope module dut $end
$var wire 8 ( addr [7:0] $end
$var wire 1 $ clk $end
$var wire 1 % cpu_req $end
$var wire 1 & cpu_write $end
$var wire 1 ) miss $end
$var wire 1 ' rst $end
$var wire 1 * valid $end
$var wire 1 + tag_write_en $end
$var wire 4 , tag [3:0] $end
$var wire 4 - stored_tag [3:0] $end
$var wire 3 . state [2:0] $end
$var wire 2 / offset [1:0] $end
$var wire 32 0 miss_count [31:0] $end
$var wire 1 1 mem_write $end
$var wire 1 2 mem_read $end
$var wire 2 3 index [1:0] $end
$var wire 32 4 hit_count [31:0] $end
$var wire 1 " hit $end
$var wire 1 5 dirty_write_en $end
$var wire 1 6 dirty $end
$var wire 1 7 data_write_en $end
$var wire 1 8 cpu_ready $end
$var wire 128 9 cache_block [127:0] $end
$var wire 128 : block_data [127:0] $end
$scope module ctrl_inst $end
$var wire 1 $ clk $end
$var wire 1 % cpu_req $end
$var wire 1 & cpu_write $end
$var wire 1 ' rst $end
$var wire 1 " hit $end
$var wire 1 6 dirty $end
$var reg 1 8 cpu_ready $end
$var reg 1 7 data_write_en $end
$var reg 1 5 dirty_write_en $end
$var reg 1 2 mem_read $end
$var reg 1 1 mem_write $end
$var reg 3 ; next_state [2:0] $end
$var reg 3 < state [2:0] $end
$var reg 1 + tag_write_en $end
$upscope $end
$scope module data_inst $end
$var wire 128 = block_out [127:0] $end
$var wire 1 $ clk $end
$var wire 2 > offset [1:0] $end
$var wire 32 ? write_data [31:0] $end
$var wire 1 7 write_en $end
$var wire 1 @ write_word_en $end
$var wire 2 A index [1:0] $end
$var wire 128 B block_in [127:0] $end
$var integer 32 C i [31:0] $end
$upscope $end
$scope module dirty_inst $end
$var wire 1 $ clk $end
$var wire 1 D dirty_in $end
$var wire 1 6 dirty_out $end
$var wire 1 5 write_en $end
$var wire 2 E index [1:0] $end
$var integer 32 F i [31:0] $end
$upscope $end
$scope module lookup_inst $end
$var wire 8 G addr [7:0] $end
$var wire 1 " hit $end
$var wire 1 * valid $end
$var wire 4 H tag [3:0] $end
$var wire 4 I stored_tag [3:0] $end
$var wire 2 J offset [1:0] $end
$var wire 2 K index [1:0] $end
$upscope $end
$scope module mem_inst $end
$var wire 32 L addr [31:0] $end
$var wire 1 $ clk $end
$var wire 1 2 mem_read $end
$var wire 1 1 mem_write $end
$var wire 128 M write_block [127:0] $end
$var wire 32 N block_addr [31:0] $end
$var reg 128 O block_data [127:0] $end
$var reg 1 P mem_ready $end
$var integer 32 Q i [31:0] $end
$upscope $end
$scope module stats_inst $end
$var wire 1 $ clk $end
$var wire 1 " hit $end
$var wire 1 ) miss $end
$var wire 1 ' rst $end
$var reg 32 R hit_count [31:0] $end
$var reg 32 S miss_count [31:0] $end
$upscope $end
$scope module tag_inst $end
$var wire 1 $ clk $end
$var wire 2 T index [1:0] $end
$var wire 4 U tag_in [3:0] $end
$var wire 4 V tag_out [3:0] $end
$var wire 1 W valid_in $end
$var wire 1 * valid_out $end
$var wire 1 + write_en $end
$var integer 32 X i [31:0] $end
$upscope $end
$upscope $end
$upscope $end
$enddefinitions $end
#0
$dumpvars
b100 X
1W
b0 V
b0 U
b0 T
b0 S
b0 R
b100000000 Q
xP
bx O
b0 N
b0 M
b0 L
b0 K
b0 J
b0 I
b0 H
b0 G
b100 F
b0 E
1D
b100 C
bx B
b0 A
z@
bz ?
bz >
b0 =
b0 <
b0 ;
bx :
b0 9
08
07
06
05
b0 4
b0 3
02
01
b0 0
b0 /
b0 .
b0 -
b0 ,
0+
0*
0)
b0 (
1'
0&
0%
0$
b0 #
0"
b0 !
$end
#5000
0P
1$
#10000
0$
#15000
1$
#20000
1)
b1 ;
b100 N
b1 3
b1 A
b1 E
b1 K
b1 T
b10 /
b10 J
0$
1%
b110 L
b110 #
b110 (
b110 G
0'
#25000
b11 ;
b1 !
b1 .
b1 <
b1 0
b1 S
1$
#30000
0$
#35000
12
b101 ;
b10 0
b10 S
b11 !
b11 .
b11 <
1$
#40000
0$
#45000
17
1+
02
b110 ;
b101 !
b101 .
b101 <
b11 0
b11 S
1P
b111000000000000000000000000000001100000000000000000000000000000010100000000000000000000000000000100 :
b111000000000000000000000000000001100000000000000000000000000000010100000000000000000000000000000100 B
b111000000000000000000000000000001100000000000000000000000000000010100000000000000000000000000000100 O
1$
#50000
0$
#55000
0)
18
07
0+
b0 ;
1"
b100 0
b100 S
b110 !
b110 .
b110 <
0P
b111000000000000000000000000000001100000000000000000000000000000010100000000000000000000000000000100 9
b111000000000000000000000000000001100000000000000000000000000000010100000000000000000000000000000100 =
b111000000000000000000000000000001100000000000000000000000000000010100000000000000000000000000000100 M
1*
1$
#60000
0$
0%
#65000
08
b0 !
b0 .
b0 <
b1 4
b1 R
1$
#70000
0$
#75000
b10 4
b10 R
1$
#80000
b1 ;
0$
1%
#85000
b110 ;
b1 !
b1 .
b1 <
b11 4
b11 R
1$
#90000
0$
#95000
18
b0 ;
b100 4
b100 R
b110 !
b110 .
b110 <
1$
#100000
0$
#105000
08
b1 ;
b0 !
b0 .
b0 <
b101 4
b101 R
1$
#110000
b0 ;
0$
0%
#115000
b110 4
b110 R
1$
#120000
0$
#125000
b111 4
b111 R
1$
#130000
b1 ;
0$
1%
1&
#135000
b10 ;
b1000 4
b1000 R
b1 !
b1 .
b1 <
1$
#140000
0$
#145000
15
17
b110 ;
b10 !
b10 .
b10 <
b1001 4
b1001 R
1$
#150000
0$
#155000
18
05
07
b0 ;
b1010 4
b1010 R
b110 !
b110 .
b110 <
16
1$
#160000
0$
0&
0%
#165000
08
b0 !
b0 .
b0 <
b1011 4
b1011 R
1$
#170000
0$
#175000
b1100 4
b1100 R
1$
#180000
1)
0"
b1 ;
b10100 N
b1 ,
b1 H
b1 U
0$
1%
b10110 L
b10110 #
b10110 (
b10110 G
#185000
b11 ;
b1 !
b1 .
b1 <
b101 0
b101 S
1$
#190000
0$
#195000
12
b100 ;
b110 0
b110 S
b11 !
b11 .
b11 <
1$
#200000
0$
#205000
11
02
b101 ;
b100 !
b100 .
b100 <
b111 0
b111 S
1P
b10111000000000000000000000000000101100000000000000000000000000001010100000000000000000000000000010100 :
b10111000000000000000000000000000101100000000000000000000000000001010100000000000000000000000000010100 B
b10111000000000000000000000000000101100000000000000000000000000001010100000000000000000000000000010100 O
1$
#210000
0$
#215000
17
1+
01
b110 ;
b1000 0
b1000 S
b101 !
b101 .
b101 <
1P
1$
#220000
0$
#225000
0)
18
07
0+
b0 ;
1"
b110 !
b110 .
b110 <
b1001 0
b1001 S
b1 -
b1 I
b1 V
b10111000000000000000000000000000101100000000000000000000000000001010100000000000000000000000000010100 9
b10111000000000000000000000000000101100000000000000000000000000001010100000000000000000000000000010100 =
b10111000000000000000000000000000101100000000000000000000000000001010100000000000000000000000000010100 M
0P
1$
#230000
0$
#235000
08
b1 ;
b1101 4
b1101 R
b0 !
b0 .
b0 <
1$
#240000
b0 ;
0$
0%
#245000
b1110 4
b1110 R
1$
#250000
0$
#255000
b1111 4
b1111 R
1$
#260000
0$
#265000
b10000 4
b10000 R
1$
#270000
0$
#275000
b10001 4
b10001 R
1$
#280000
0$
#285000
b10010 4
b10010 R
1$
