cache_controller_project/rtl/main_memory.v
module  main_memory (
    input clk,
    input [31:0] addr,
    input mem_read,
    input mem_write,
    input [127:0] write_block,
    output reg [127:0] block_data,
    output reg mem_ready
);
reg [31:0] mem [0:255];
integer i;
initial begin
    for(i=0;i<256;i=i+1)
        mem[i]=i;
end
wire [31:0] block_addr;
assign block_addr = {addr[31:2],2'b00};
always @(posedge clk)
begin
    mem_ready <= 0;
    if(mem_read)
    begin
        block_data <= {
            mem[block_addr + 3],
            mem[block_addr + 2],
            mem[block_addr + 1],
            mem[block_addr]
        };
        mem_ready <= 1;
    end
    if(mem_write)
    begin
        mem[block_addr]     <= write_block[31:0];
        mem[block_addr + 1] <= write_block[63:32];
        mem[block_addr + 2] <= write_block[95:64];
        mem[block_addr + 3] <= write_block[127:96];
        mem_ready <= 1;
    end
end
endmodule

cache_controller_project/tb/tb_main_memory_write.v
`timescale 1ns/1ps

module tb_main_memory_write;

reg clk;

reg mem_read;
reg mem_write;

reg [31:0] addr;

reg [127:0] write_block;

wire [127:0] block_data;
wire mem_ready;

main_memory dut(

    .clk(clk),

    .mem_read(mem_read),
    .mem_write(mem_write),

    .addr(addr),

    .write_block(write_block),

    .block_data(block_data),
    .mem_ready(mem_ready)

);

always #5 clk = ~clk;

initial begin

    $dumpfile("main_memory_write.vcd");
    $dumpvars(0,tb_main_memory_write);

end

initial begin

    clk = 0;

    mem_read = 0;
    mem_write = 0;

    addr = 0;

    write_block = 0;

    //----------------------------------
    // WRITE BLOCK
    //----------------------------------

    #10;

    addr = 8;

    write_block = {

        32'd400,
        32'd300,
        32'd200,
        32'd100

    };

    mem_write = 1;

    #10;

    mem_write = 0;

    //----------------------------------
    // READ SAME BLOCK
    //----------------------------------

    #20;

    mem_read = 1;

    #10;

    mem_read = 0;

    //----------------------------------
    // CHECK RESULTS
    //----------------------------------

    #20;

    $display("");
    $display("Expected Word0 = 100");
    $display("Actual   Word0 = %d", block_data[31:0]);

    $display("Expected Word1 = 200");
    $display("Actual   Word1 = %d", block_data[63:32]);

    $display("Expected Word2 = 300");
    $display("Actual   Word2 = %d", block_data[95:64]);

    $display("Expected Word3 = 400");
    $display("Actual   Word3 = %d", block_data[127:96]);

    #20;

    $finish;

end

initial begin

    $monitor(
        "Time=%0t clk=%b read=%b write=%b addr=%d ready=%b block=%h",
        $time,
        clk,
        mem_read,
        mem_write,
        addr,
        mem_ready,
        block_data
    );

end

endmodule

cache_controller_project/waves/main_memory_write.vcd
$date
	Wed Jun 24 17:41:09 2026
$end
$version
	Icarus Verilog
$end
$timescale
	1ps
$end
$scope module tb_main_memory_write $end
$var wire 1 ! mem_ready $end
$var wire 128 " block_data [127:0] $end
$var reg 32 # addr [31:0] $end
$var reg 1 $ clk $end
$var reg 1 % mem_read $end
$var reg 1 & mem_write $end
$var reg 128 ' write_block [127:0] $end
$scope module dut $end
$var wire 32 ( addr [31:0] $end
$var wire 1 $ clk $end
$var wire 1 % mem_read $end
$var wire 1 & mem_write $end
$var wire 128 ) write_block [127:0] $end
$var wire 32 * block_addr [31:0] $end
$var reg 128 + block_data [127:0] $end
$var reg 1 ! mem_ready $end
$var integer 32 , i [31:0] $end
$upscope $end
$upscope $end
$enddefinitions $end
#0
$dumpvars
b100000000 ,
bx +
b0 *
b0 )
b0 (
b0 '
0&
0%
0$
b0 #
bx "
x!
$end
#5000
0!
1$
#10000
b1000 *
0$
1&
b110010000000000000000000000000001001011000000000000000000000000001100100000000000000000000000000001100100 '
b110010000000000000000000000000001001011000000000000000000000000001100100000000000000000000000000001100100 )
b1000 #
b1000 (
#15000
1!
1$
#20000
0$
0&
#25000
0!
1$
#30000
0$
#35000
1$
#40000
0$
1%
#45000
1!
b110010000000000000000000000000001001011000000000000000000000000001100100000000000000000000000000001100100 "
b110010000000000000000000000000001001011000000000000000000000000001100100000000000000000000000000001100100 +
1$
#50000
0$
0%
#55000
0!
1$
